{
  "generated_at": "2026-04-20T21:30:06+00:00",
  "prices": {
    "commodities": {
      "Gold": {
        "ticker": "GC=F",
        "price": 4841.0,
        "change": -16.600098,
        "pct_change": -0.342,
        "date": "2026-04-20"
      },
      "Silver": {
        "ticker": "SI=F",
        "price": 79.870003,
        "change": -1.867996,
        "pct_change": -2.285,
        "date": "2026-04-20"
      },
      "Soybeans": {
        "ticker": "ZS=F",
        "price": 1180.75,
        "change": 13.5,
        "pct_change": 1.157,
        "date": "2026-04-20"
      },
      "Sugar #11 (Raw)": {
        "ticker": "SB=F",
        "price": 13.63,
        "change": 0.32,
        "pct_change": 2.404,
        "date": "2026-04-20"
      }
    },
    "fx": {
      "AUD/USD": {
        "ticker": "AUDUSD=X",
        "price": 0.717684,
        "change": 0.001784,
        "pct_change": 0.249,
        "date": "2026-04-20"
      }
    },
    "indices": {
      "S&P 500": {
        "ticker": "^GSPC",
        "price": 7109.140137,
        "change": -16.919922,
        "pct_change": -0.237,
        "date": "2026-04-20"
      },
      "US 10Y Yield (%)": {
        "ticker": "^TNX",
        "price": 4.25,
        "change": 0.004,
        "pct_change": 0.094,
        "date": "2026-04-20"
      },
      "Hang Seng 50": {
        "ticker": "^HSI",
        "price": 26160.330078,
        "change": -233.929688,
        "pct_change": -0.886,
        "date": "2026-04-17"
      },
      "South Africa Top 40": {
        "ticker": "STX40.JO",
        "price": 11433.0,
        "change": -195.0,
        "pct_change": -1.677,
        "date": "2026-04-20"
      },
      "Switzerland SMI": {
        "ticker": "^SSMI",
        "price": 13284.219727,
        "change": -142.5,
        "pct_change": -1.061,
        "date": "2026-04-20"
      },
      "ASX 200 (XJO)": {
        "ticker": "^AXJO",
        "price": 8946.900391,
        "change": -8.099609,
        "pct_change": -0.09,
        "date": "2026-04-17"
      }
    },
    "stocks": {
      "Palantir": {
        "ticker": "PLTR",
        "price": 145.889999,
        "change": -0.5,
        "pct_change": -0.342,
        "date": "2026-04-20"
      },
      "McDonald's": {
        "ticker": "MCD",
        "price": 306.940002,
        "change": -4.419983,
        "pct_change": -1.42,
        "date": "2026-04-20"
      },
      "Tesla": {
        "ticker": "TSLA",
        "price": 392.5,
        "change": -8.119995,
        "pct_change": -2.027,
        "date": "2026-04-20"
      },
      "Alphabet": {
        "ticker": "GOOGL",
        "price": 337.420013,
        "change": -4.259979,
        "pct_change": -1.247,
        "date": "2026-04-20"
      },
      "Lockheed Martin": {
        "ticker": "LMT",
        "price": 581.280029,
        "change": -10.909973,
        "pct_change": -1.842,
        "date": "2026-04-20"
      },
      "RTX (Raytheon)": {
        "ticker": "RTX",
        "price": 195.789993,
        "change": -0.630005,
        "pct_change": -0.321,
        "date": "2026-04-20"
      },
      "Northrop Grumman": {
        "ticker": "NOC",
        "price": 656.97998,
        "change": -8.280029,
        "pct_change": -1.245,
        "date": "2026-04-20"
      }
    }
  },
  "news": [
    {
      "source": "BBC World",
      "title": "Outrage over Israeli soldier's vandalism of Jesus statue in Lebanon",
      "link": "https://www.bbc.com/news/articles/cpd575n1znzo?at_medium=RSS&at_campaign=rss",
      "published": "Mon, 20 Apr 2026 18:57:25 GMT",
      "matched_keywords": [
        "military"
      ]
    },
    {
      "source": "BBC World",
      "title": "Japan on high alert for 'huge' second quake after issuing tsunami warning",
      "link": "https://www.bbc.com/news/articles/czd7m7d699do?at_medium=RSS&at_campaign=rss",
      "published": "Mon, 20 Apr 2026 14:54:21 GMT",
      "matched_keywords": [
        "war",
        "earthquake",
        "tsunami"
      ]
    },
    {
      "source": "BBC World",
      "title": "What we know about the Iranian ship seized by the US",
      "link": "https://www.bbc.com/news/articles/c75kg0vdxyro?at_medium=RSS&at_campaign=rss",
      "published": "Mon, 20 Apr 2026 20:04:59 GMT",
      "matched_keywords": [
        "president"
      ]
    },
    {
      "source": "BBC World",
      "title": "Oil prices rise after Trump says Iranian ship seized",
      "link": "https://www.bbc.com/news/articles/c5yjzy35825o?at_medium=RSS&at_campaign=rss",
      "published": "Mon, 20 Apr 2026 20:33:01 GMT",
      "matched_keywords": [
        "attack",
        "oil"
      ]
    },
    {
      "source": "BBC World",
      "title": "New Zealand declares state of emergency in Wellington as floods hit",
      "link": "https://www.bbc.com/news/articles/cly75d9zvj3o?at_medium=RSS&at_campaign=rss",
      "published": "Mon, 20 Apr 2026 05:48:54 GMT",
      "matched_keywords": [
        "flood"
      ]
    },
    {
      "source": "BBC World",
      "title": "Rumen Radev's party wins Bulgarian election",
      "link": "https://www.bbc.com/news/articles/cm2kgm1zpgro?at_medium=RSS&at_campaign=rss",
      "published": "Mon, 20 Apr 2026 13:01:19 GMT",
      "matched_keywords": [
        "election"
      ]
    },
    {
      "source": "BBC World",
      "title": "Rat poison found in HiPP baby food jar in Austria, police say",
      "link": "https://www.bbc.com/news/articles/cvg07lq5ql4o?at_medium=RSS&at_campaign=rss",
      "published": "Sun, 19 Apr 2026 12:52:26 GMT",
      "matched_keywords": [
        "war"
      ]
    },
    {
      "source": "BBC World",
      "title": "Zelensky condemns US extension of Russian sanctions waiver",
      "link": "https://www.bbc.com/news/articles/c248m3z49j1o?at_medium=RSS&at_campaign=rss",
      "published": "Sun, 19 Apr 2026 09:55:22 GMT",
      "matched_keywords": [
        "war",
        "sanctions"
      ]
    }
  ]
}